pycomsa-0.1.0.dist-info/METADATA
pycomsa-0.1.0.dist-info/RECORD
pycomsa-0.1.0.dist-info/WHEEL
pycomsa-0.1.0.dist-info/licenses/COPYING
pycomsa/_comsa.pyx
pycomsa/py.typed
pycomsa/_comsa.cpython-311-x86_64-linux-gnu.so
pycomsa/CMakeLists.txt
pycomsa/__init__.py
pycomsa/_comsa.pyi
pycomsa/tests/requirements.txt
pycomsa/tests/test_reader.py
pycomsa/tests/__init__.py
pycomsa/tests/test_doctest.py
pycomsa/tests/data/trimal.sto
pycomsa/tests/data/example.004.AA.fasta
pycomsa/tests/data/trimal.msac
pycomsa/tests/data/example.004.AA.msac
pycomsa/tests/data/__init__.py
