Metadata-Version: 2.1
Name: pycomsa
Version: 0.1.0
Summary: Cython bindings and Python interface to CoMSA, a compressor for multiple-sequence alignments.
Keywords: bioinformatics,multiple,sequence,alignment,compression
Author-Email: Martin Larralde <martin.larralde@embl.de>
License:                     GNU GENERAL PUBLIC LICENSE
Classifier: Development Status :: 3 - Alpha
Classifier: Intended Audience :: Developers
Classifier: Intended Audience :: Science/Research
Classifier: License :: OSI Approved :: GNU General Public License v3 (GPLv3)
Classifier: Operating System :: OS Independent
Classifier: Programming Language :: C
Classifier: Programming Language :: Cython
Classifier: Programming Language :: Python :: 3.7
Classifier: Programming Language :: Python :: 3.8
Classifier: Programming Language :: Python :: 3.9
Classifier: Programming Language :: Python :: 3.10
Classifier: Programming Language :: Python :: 3.11
Classifier: Programming Language :: Python :: 3.12
Classifier: Programming Language :: Python :: 3.13
Classifier: Programming Language :: Python :: Implementation :: CPython
Classifier: Programming Language :: Python :: Implementation :: PyPy
Classifier: Topic :: Scientific/Engineering :: Bio-Informatics
Classifier: Topic :: Scientific/Engineering :: Medical Science Apps.
Classifier: Typing :: Typed
Project-URL: Bug tracker, https://github.com/althonos/pycomsa/issues
Project-URL: Changelog, https://github.com/althonos/pycomsa/blob/master/CHANGELOG.md
Project-URL: Builds, https://github.com/althonos/pycomsa/actions
Project-URL: Pypi, https://pypi.org/project/pycomsa
Requires-Python: >=3.7
Provides-Extra: test
Requires-Dist: importlib-resources; python_version < "3.9" and extra == "test"
